astrolabe_python/__init__.py
astrolabe_python/operator/__init__.py
astrolabe_python/operator/base.py
astrolabe_python/operator/builtin.py
astrolabe_python/pipeline/__init__.py
astrolabe_python/pipeline/core.py
astrolabe_python/pipeline/ray.py
astrolabe_python/pipeline/runner.py
astrolabe_python/pipeline/spark.py
astrolabe_python/schema/__init__.py
astrolabe_python/schema/dataset.py
astrolabe_python/schema/interaction.py
astrolabe_python/schema/sample.py
astrolabe_python-0.1.2.dist-info/METADATA
astrolabe_python-0.1.2.dist-info/WHEEL
astrolabe_python-0.1.2.dist-info/top_level.txt
astrolabe_python-0.1.2.dist-info/RECORD
