Metadata-Version: 2.4
Name: astrolabe-python
Version: 0.1.2
Summary: LLM Pipeline SDK
Author: Astrolabe Team
License: MIT
Project-URL: Homepage, https://github.com/astrolabe/astrolabe-python
Project-URL: Documentation, https://github.com/astrolabe/astrolabe-python#readme
Project-URL: Repository, https://github.com/astrolabe/astrolabe-python
Keywords: llm,pipeline,data,ml,ai
Classifier: Development Status :: 3 - Alpha
Classifier: Intended Audience :: Developers
Classifier: License :: OSI Approved :: MIT License
Classifier: Programming Language :: Python :: 3
Classifier: Programming Language :: Python :: 3.9
Classifier: Programming Language :: Python :: 3.10
Classifier: Programming Language :: Python :: 3.11
Classifier: Programming Language :: Python :: 3.12
Classifier: Topic :: Scientific/Engineering :: Artificial Intelligence
Requires-Python: >=3.9
Requires-Dist: pydantic>=2.0.0
Provides-Extra: spark
Requires-Dist: pyspark>=3.0.0; extra == "spark"
Provides-Extra: ray
Requires-Dist: ray>=2.0.0; extra == "ray"
Provides-Extra: dev
Requires-Dist: pytest>=7.0.0; extra == "dev"
Requires-Dist: pytest-cov>=4.0.0; extra == "dev"
Requires-Dist: black>=23.0.0; extra == "dev"
Requires-Dist: ruff>=0.1.0; extra == "dev"
